jirahhh/__init__.py
jirahhh/__main__.py
jirahhh/cli.py
jirahhh/client.py
jirahhh/convert.py
jirahhh/issues.py
jirahhh-0.1.0.dist-info/METADATA
jirahhh-0.1.0.dist-info/WHEEL
jirahhh-0.1.0.dist-info/entry_points.txt
jirahhh-0.1.0.dist-info/licenses/LICENSE
jirahhh-0.1.0.dist-info/RECORD
