Metadata-Version: 2.4
Name: jirahhh
Version: 0.1.0
Summary: Utilities for creating and managing Jira issues with proper formatting and markdown support
License-Expression: Apache-2.0
License-File: LICENSE
Requires-Python: >=3.8
Requires-Dist: jira>=3.5.0
Requires-Dist: pypandoc>=1.11
Requires-Dist: pyyaml>=6.0
